sync/__init__.py
sync/__main__.py
sync/__version__.py
sync/cli/Main.py
sync/cli/Parameters.py
sync/cli/__init__.py
sync/core/Check.py
sync/core/Config.py
sync/core/Index.py
sync/core/Migrate.py
sync/core/Pull.py
sync/core/Sync.py
sync/core/__init__.py
sync/error/ConfigError.py
sync/error/MagiskModuleError.py
sync/error/Result.py
sync/error/__init__.py
sync/model/ArchiveIO.py
sync/model/AttrDict.py
sync/model/ConfigJson.py
sync/model/JsonIO.py
sync/model/LocalModule.py
sync/model/MagiskUpdateJson.py
sync/model/ModuleFeatures.py
sync/model/ModuleManager.py
sync/model/ModuleNote.py
sync/model/ModulesJson.py
sync/model/RootSolutions.py
sync/model/TrackJson.py
sync/model/TrackOptions.py
sync/model/UpdateJson.py
sync/model/__init__.py
sync/track/BaseTracks.py
sync/track/GithubTracks.py
sync/track/LocalTracks.py
sync/track/__init__.py
sync/utils/GitHubGraphQLAPI.py
sync/utils/GitUtils.py
sync/utils/HttpUtils.py
sync/utils/Log.py
sync/utils/Sitemap.py
sync/utils/StrUtils.py
sync/utils/__init__.py
zipxz/__init__.py
zipxz/_patcher.py
zipxz/_zipfile.py
mmrl_util-2.15.24.dist-info/LICENSE
mmrl_util-2.15.24.dist-info/METADATA
mmrl_util-2.15.24.dist-info/WHEEL
mmrl_util-2.15.24.dist-info/entry_points.txt
mmrl_util-2.15.24.dist-info/top_level.txt
mmrl_util-2.15.24.dist-info/RECORD
