Metadata-Version: 2.1
Name: mmrl-util
Version: 2.15.24
Summary: A tool to build your own Magisk Modules Repository
Home-page: https://github.com/Googlers-Repo/magisk-modules-repo-util
Author: Der_Googler & Sanmer
Author-email: jimmy@dergooglr.com
License: GPL-3.0
Requires-Python: >=3.7
License-File: LICENSE
Requires-Dist: gitpython >=3.1.37
Requires-Dist: pygithub >=1.59.0
Requires-Dist: python-dateutil >=2.8.2
Requires-Dist: python-magic >=0.4.27
Requires-Dist: pyyaml >=6.0.2
Requires-Dist: requests >=2.31.0
Requires-Dist: tabulate >=0.9.0
Requires-Dist: validators >=0.28.3
